{"cameraMode":{"drawMode":0,"name":"Shaded","section":"Shading Mode"},"sceneLighting":true,"audioPlay":false,"sceneViewState":{"m_AlwaysRefresh":false,"showFog":true,"showSkybox":true,"showFlares":true,"showImageEffects":true,"showParticleSystems":true,"showVisualEffectGraphs":true,"m_FxEnabled":true},"in2DMode":false,"pivot":{"x":289.8121032714844,"y":169.2932586669922,"z":213.0138397216797},"rotation":{"x":0.3043094873428345,"y":-0.6012226939201355,"z":0.26482993364334109,"w":0.6899222135543823},"size":54.76301574707031,"orthographic":false}